tkfilebrowser/__init__.py
tkfilebrowser/__main__.py
tkfilebrowser/autoscrollbar.py
tkfilebrowser/constants.py
tkfilebrowser/filebrowser.py
tkfilebrowser/functions.py
tkfilebrowser/path_button.py
tkfilebrowser/recent_files.py
tkfilebrowser/tooltip.py
tkfilebrowser/images/desktop.png
tkfilebrowser/images/dossier.png
tkfilebrowser/images/dossier_link.png
tkfilebrowser/images/drive.png
tkfilebrowser/images/file.png
tkfilebrowser/images/file_link.png
tkfilebrowser/images/folder.png
tkfilebrowser/images/folder_link.png
tkfilebrowser/images/home.png
tkfilebrowser/images/link_broken.png
tkfilebrowser/images/new_folder.png
tkfilebrowser/images/recent.png
tkfilebrowser/images/recent_24.png
tkfilebrowser-2.3.1.dist-info/LICENSE.txt
tkfilebrowser-2.3.1.dist-info/METADATA
tkfilebrowser-2.3.1.dist-info/WHEEL
tkfilebrowser-2.3.1.dist-info/top_level.txt
tkfilebrowser-2.3.1.dist-info/RECORD
