Metadata-Version: 2.1
Name: tkfilebrowser
Version: 2.3.1
Summary: File browser for Tkinter, alternative to tkinter.filedialog in linux with GTK bookmarks support.
Home-page: https://github.com/j4321/tkFileBrowser
Author: Juliette Monsel
Author-email: j_4321@protonmail.com
License: GPLv3
Keywords: tkinter,filedialog,filebrowser
Platform: UNKNOWN
Classifier: Development Status :: 5 - Production/Stable
Classifier: Intended Audience :: Developers
Classifier: Topic :: Software Development :: Widget Sets
Classifier: Topic :: Software Development :: Libraries :: Python Modules
Classifier: License :: OSI Approved :: GNU General Public License v3 (GPLv3)
Classifier: Programming Language :: Python :: 2.7
Classifier: Programming Language :: Python :: 3
Classifier: Programming Language :: Python :: 3.4
Classifier: Programming Language :: Python :: 3.5
Classifier: Programming Language :: Python :: 3.6
Classifier: Programming Language :: Python :: 3.7
Classifier: Natural Language :: English
Classifier: Natural Language :: French
Classifier: Operating System :: POSIX :: Linux
Classifier: Operating System :: Microsoft :: Windows
Provides-Extra: tk<8.6.0
